{
  "$schema": "https://raw.githubusercontent.com/jsonresume/resume-schema/v1.0.0/schema.json",
  "basics": {
    "name": "Roberto Santos Mazutti Kosmel",
    "label": "Desenvolvedor Full-Stack Jr",
    "email": "roberto.m.kosmel@gmail.com",
    "phone": "+55 19 98926-3577",
    "url": "https://github.com/rkosmel",
    "location": {
      "city": "São José dos Campos",
      "region": "SP",
      "countryCode": "BR"
    },
    "profiles": [
      {
        "network": "GitHub",
        "username": "rkosmel",
        "url": "https://github.com/rkosmel"
      },
      {
        "network": "LinkedIn",
        "username": "robertokosmel",
        "url": "https://www.linkedin.com/in/robertokosmel/"
      }
    ],
    "summary": "Desenvolvedor Full-Stack Jr com foco em React/Next.js, Node.js (Express) e PostgreSQL. Experiência prática com deploy e manutenção em produção na AWS (EC2, RDS, S3), além de troubleshooting e entregas end-to-end."
  },
  "work": [
    {
      "name": "Blue Exams / The Mindville / MBA No Brainer",
      "position": "Estagiário de Desenvolvimento (Full-Stack)",
      "startDate": "2025-04-22",
      "endDate": "2025-12-19",
      "summary": "Atuação em múltiplos produtos web com foco em entrega, estabilidade em produção e suporte a operações em cloud.",
      "highlights": [
        "Desenvolvimento e evolução de aplicações web com foco em entrega end-to-end.",
        "Criação e consumo de APIs REST (endpoints Next.js, Stripe, NextAuth, Chatwoot, backend Node.js).",
        "Integração com banco de dados PostgreSQL e rotinas de manutenção/debug.",
        "Suporte a deploy e operação em ambiente AWS (EC2, RDS, S3) e Linux."
      ]
    }
  ],
  "education": [
    {
      "institution": "UNIFESP — Universidade Federal de São Paulo (São José dos Campos)",
      "area": "Engenharia de Computação",
      "studyType": "Graduação (em andamento)",
      "startDate": "2023",
      "endDate": "2027-06"
    },
    {
      "institution": "UNIFESP — Universidade Federal de São Paulo (São José dos Campos)",
      "area": "Bacharelado em Ciência e Tecnologia (BCT)",
      "studyType": "Graduação",
      "startDate": "2021",
      "endDate": "2023"
    }
  ],
  "skills": [
    {
      "name": "Linguagens",
      "keywords": ["JavaScript", "TypeScript", "Python", "C/C++", "SQL"]
    },
    {
      "name": "Full-Stack",
      "keywords": ["Next.js", "React", "Node.js", "Express", "HTML", "CSS", "Tailwind CSS", "REST", "JWT", "NextAuth"]
    },
    {
      "name": "Dados",
      "keywords": ["PostgreSQL", "Prisma", "JSON", "DBeaver", "Análise de dados"]
    },
    {
      "name": "Cloud & DevOps",
      "keywords": ["AWS (EC2, RDS, S3 + múltiplos serviços)", "Docker", "Linux", "Nginx"]
    },
    {
      "name": "Automação & Integrações",
      "keywords": ["Stripe (pagamentos)", "Zapier", "Twilio", "n8n (em estudo)"]
    },
    {
      "name": "Ferramentas",
      "keywords": ["Git", "VS Code", "Microsoft Office (Avançado)"]
    }
  ],
  "languages": [
    {
      "language": "Português",
      "fluency": "Nativo"
    },
    {
      "language": "Ingl\u00eas",
      "fluency": "Avan\u00e7ado"
    }
  ],
  "projects": [
    {
      "name": "Blue Exams — Plataforma de simulados (assinatura)",
      "description": "Plataforma web de simulados por assinatura, com autenticação, billing e dashboard.",
      "highlights": [
        "Implementação de fluxos principais (login e dashboard) em Next.js/React.",
        "Consumo de APIs REST para autenticação (NextAuth) e pagamentos (Stripe).",
        "Autenticação e controle de acesso via NextAuth, com billing/assinatura via Stripe.",
        "Persistência em PostgreSQL via Prisma, com manutenção e correções em produção."
      ],
      "keywords": ["Next.js", "React", "NextAuth", "Stripe", "PostgreSQL", "Prisma"],
      "url": "https://github.com/rkosmel/portfolio-roberto/blob/main/case-studies/blueexams-mock-exam-platform.md"
    },
    {
      "name": "Compilador para linguagem C-",
      "description": "Compilador acadêmico implementado em C.",
      "highlights": ["Análise léxica, sintática e semântica."],
      "keywords": ["C", "Compiladores"],
      "entity": "UNIFESP"
    },
    {
      "name": "Blue Exams \u2014 Landing page (site institucional)",
      "description": "Site institucional est\u00e1tico com deploy em servidor Linux.",
      "highlights": ["Site em HTML/CSS/JavaScript com opera\u00e7\u00e3o em AWS EC2 + Nginx e TLS/Let's Encrypt."],
      "keywords": ["HTML", "CSS", "JavaScript", "AWS EC2", "Nginx", "TLS"],
      "url": "https://github.com/rkosmel/portfolio-roberto/blob/main/case-studies/blueexams-landing.md"
    },
    {
      "name": "Electric Ways \u2014 Rotas para ve\u00edculos el\u00e9tricos",
      "description": "Projeto acad\u00eamico para tra\u00e7ar rotas considerando autonomia e paradas para recarga.",
      "highlights": ["Modelagem de rotas com restri\u00e7\u00f5es de autonomia e recarga."],
      "entity": "UNIFESP"
    }
  ]
}
